{
  "inputsBar": {
    "gap": {
      "default": {
        "$type": "dimension",
        "$value": "{size.pos.xxsmall}"
      },
      "inner": {
        "$type": "dimension",
        "$value": "{size.null}"
      }
    },
    "width": {
      "$type": "dimension",
      "$value": "{size.pos.xlarge}"
    },
    "padding": {
      "top": {
        "$type": "dimension",
        "$value": "{size.null}"
      },
      "right": {
        "$type": "dimension",
        "$value": "{size.pos.unit}"
      },
      "bottom": {
        "$type": "dimension",
        "$value": "{size.null}"
      },
      "left": {
        "$type": "dimension",
        "$value": "{size.pos.unit}"
      }
    },
    "margin": {
      "top": {
        "$type": "dimension",
        "$value": "{size.null}"
      },
      "right": {
        "$type": "dimension",
        "$value": "{size.neg.unit}"
      },
      "bottom": {
        "$type": "dimension",
        "$value": "{size.null}"
      },
      "left": {
        "$type": "dimension",
        "$value": "{size.neg.unit}"
      }
    },
    "radius": {
      "$type": "dimension",
      "$value": "{border.radius.xlarge}"
    },
    "border": {
      "color": {
        "$type": "color",
        "$value": "{penpot.color.accent.primary.default}"
      },
      "width": {
        "$type": "dimension",
        "$value": "{size.pos.unit}"
      }
    },
    "input": {
      "radius": {
        "$type": "dimension",
        "$value": "{border.radius.null}"
      }
    }
  }
}